waveboxgen/__init__.py
waveboxgen/main.py
waveboxgen/templates/__init__.py
waveboxgen/utils/__init__.py
waveboxgen/utils/converter.py
waveboxgen_adorufus-0.0.1.dist-info/LICENSE
waveboxgen_adorufus-0.0.1.dist-info/METADATA
waveboxgen_adorufus-0.0.1.dist-info/WHEEL
waveboxgen_adorufus-0.0.1.dist-info/entry_points.txt
waveboxgen_adorufus-0.0.1.dist-info/top_level.txt
waveboxgen_adorufus-0.0.1.dist-info/RECORD
